{
	"info": {
		"_postman_id": "c60c2f94-6236-4cf1-beb4-c04bd81518d8",
		"name": "StreamAMGApp",
		"schema": "https://schema.getpostman.com/json/collection/v2.1.0/collection.json",
		"_exporter_id": "36158434"
	},
	"item": [
		{
			"name": "/",
			"request": {
				"method": "GET",
				"header": [],
				"url": {
					"raw": "http://localhost:3000/",
					"protocol": "http",
					"host": [
						"localhost"
					],
					"port": "3000",
					"path": [
						""
					]
				}
			},
			"response": []
		},
		{
			"name": "/metadata",
			"request": {
				"method": "POST",
				"header": [],
				"body": {
					"mode": "raw",
					"raw": "{\n    \"title\" : \"test\",\n    \"description\" : \"test description\",\n    \"duration\" : \"test duration\",\n    \"categories\" : [\n        \"category1\",\n        \"category2\",\n        \"category3\"\n    ]    \n}",
					"options": {
						"raw": {
							"language": "json"
						}
					}
				},
				"url": {
					"raw": "http://localhost:3000/metadata/",
					"protocol": "http",
					"host": [
						"localhost"
					],
					"port": "3000",
					"path": [
						"metadata",
						""
					]
				}
			},
			"response": []
		},
		{
			"name": "/metadata/1",
			"request": {
				"method": "POST",
				"header": [],
				"body": {
					"mode": "raw",
					"raw": "{\n    \"title\" : \"test2\",\n    \"description\" : \"test description 2\",\n    \"duration\" : \"test duration 2\",\n    \"categories\" : [\n        \"category4\",\n        \"category5\",\n        \"category6\"\n    ]    \n}",
					"options": {
						"raw": {
							"language": "json"
						}
					}
				},
				"url": {
					"raw": "http://localhost:3000/metadata/1",
					"protocol": "http",
					"host": [
						"localhost"
					],
					"port": "3000",
					"path": [
						"metadata",
						"1"
					]
				}
			},
			"response": []
		},
		{
			"name": "/metadata",
			"request": {
				"method": "GET",
				"header": [],
				"url": {
					"raw": "http://localhost:3000/metadata/",
					"protocol": "http",
					"host": [
						"localhost"
					],
					"port": "3000",
					"path": [
						"metadata",
						""
					]
				}
			},
			"response": []
		},
		{
			"name": "/metadata/1",
			"request": {
				"method": "GET",
				"header": [],
				"url": {
					"raw": "http://localhost:3000/metadata/1",
					"protocol": "http",
					"host": [
						"localhost"
					],
					"port": "3000",
					"path": [
						"metadata",
						"1"
					]
				}
			},
			"response": []
		},
		{
			"name": "/metadata",
			"request": {
				"method": "DELETE",
				"header": [],
				"body": {
					"mode": "raw",
					"raw": "{\"name\" : \"test\"}",
					"options": {
						"raw": {
							"language": "json"
						}
					}
				},
				"url": {
					"raw": "http://localhost:3000/metadata/",
					"protocol": "http",
					"host": [
						"localhost"
					],
					"port": "3000",
					"path": [
						"metadata",
						""
					]
				}
			},
			"response": []
		},
		{
			"name": "/metadata/1",
			"request": {
				"method": "DELETE",
				"header": [],
				"body": {
					"mode": "raw",
					"raw": "{\"name\" : \"test\"}",
					"options": {
						"raw": {
							"language": "json"
						}
					}
				},
				"url": {
					"raw": "http://localhost:3000/metadata/1",
					"protocol": "http",
					"host": [
						"localhost"
					],
					"port": "3000",
					"path": [
						"metadata",
						"1"
					]
				}
			},
			"response": []
		}
	]
}